.bumpversion.cfg
.coveragerc
.editorconfig
.readthedocs.yml
AUTHORS.rst
CODE_OF_CONDUCT.md
MANIFEST.in
docs/Makefile
docs/authors.rst
docs/conf.py
docs/contributing.rst
docs/index.rst
docs/license.rst
docs/requirements.txt
erin/__init__.py
erin/__main__.py
erin/app.py
erin/cli/__init__.py
erin/cli/scaffold.py
erin/cli/start.py
erin/client.py
erin/core/__init__.py
erin/core/exceptions.py
erin/core/loggers.py
erin/core/schema.py
erin/core/utils.py
erin/db/__init__.py
erin/db/abc.py
erin/db/drivers/__init__.py
erin/db/drivers/mongo.py
erin/utils.py
poetry.lock
tests/__init__.py
tests/test_configs.py
tests/test_plugins.py
tox.ini
erin-0.1.0a4.dist-info/entry_points.txt
erin-0.1.0a4.dist-info/LICENSE
erin-0.1.0a4.dist-info/WHEEL
erin-0.1.0a4.dist-info/METADATA
erin-0.1.0a4.dist-info/RECORD
