Metadata-Version: 2.1
Name: erin
Version: 0.1.0a4
Summary: Fully Fledged Discord Bot Framework
Home-page: https://github.com/OpenDebates/Erin
License: Apache-2.0
Keywords: discord,bot,api,framework,cog
Author: Taven
Author-email: taven@outlook.in
Requires-Python: >=3.8,<4.0
Classifier: Development Status :: 2 - Pre-Alpha
Classifier: Environment :: Console
Classifier: Framework :: AsyncIO
Classifier: Intended Audience :: Developers
Classifier: License :: OSI Approved :: Apache Software License
Classifier: Natural Language :: English
Classifier: Operating System :: OS Independent
Classifier: Programming Language :: Python :: 3
Classifier: Programming Language :: Python :: 3 :: Only
Classifier: Programming Language :: Python :: 3.8
Classifier: Programming Language :: Python :: 3.9
Classifier: Topic :: Communications :: Chat
Requires-Dist: PyNaCl (>=1.4.0,<2.0.0)
Requires-Dist: certifi (>=2021.5.30,<2022.0.0)
Requires-Dist: cookiecutter (>=1.7.3,<2.0.0)
Requires-Dist: discord.py (>=1.7.3,<2.0.0)
Requires-Dist: dnspython (>=2.1.0,<3.0.0)
Requires-Dist: motor (>=2.4.0,<3.0.0)
Requires-Dist: schema (>=0.7.4,<0.8.0)
Requires-Dist: toml (>=0.10.2,<0.11.0)
Requires-Dist: verboselogs (>=1.7,<2.0)
Project-URL: Documentation, https://erin.readthedocs.io
Project-URL: Repository, https://github.com/OpenDebates/Erin
